[
  {
    "dateCreated": "14/12/2024",
    "formId": "S2406-0001",
    "patientReference": "21323132123",
    "clinicName": "Clinic name",
    "formStatus": "INCOMPLETE"
  },
  {
    "dateCreated": "14/12/2024",
    "formId": "S2406-0002",
    "patientReference": "21323132124",
    "clinicName": "Clinic name",
    "formStatus": "INCOMPLETE"
  },
  {
    "dateCreated": "14/12/2024",
    "formId": "S2406-0003",
    "patientReference": "21323132125",
    "clinicName": "Clinic name",
    "formStatus": "INCOMPLETE"
  },
  {
    "dateCreated": "14/12/2024",
    "formId": "S2406-0004",
    "patientReference": "21323132126",
    "clinicName": "Clinic name",
    "formStatus": "INCOMPLETE"
  },
  {
    "dateCreated": "14/12/2024",
    "formId": "S2406-0005",
    "patientReference": "21323132127",
    "clinicName": "Clinic name",
    "formStatus": "INCOMPLETE"
  },
  {
    "dateCreated": "14/12/2024",
    "formId": "S2406-0006",
    "patientReference": "21323132128",
    "clinicName": "Clinic name",
    "formStatus": "INCOMPLETE"
  },
  {
    "dateCreated": "14/12/2024",
    "formId": "S2406-0007",
    "patientReference": "21323132129",
    "clinicName": "Clinic name",
    "formStatus": "INCOMPLETE"
  },
  {
    "dateCreated": "14/12/2024",
    "formId": "S2406-0008",
    "patientReference": "21323132130",
    "clinicName": "Clinic name",
    "formStatus": "INCOMPLETE"
  },
  {
    "dateCreated": "14/12/2024",
    "formId": "S2406-0009",
    "patientReference": "21323132131",
    "clinicName": "Clinic name",
    "formStatus": "INCOMPLETE"
  },
  {
    "dateCreated": "14/12/2024",
    "formId": "S2406-0010",
    "patientReference": "21323132132",
    "clinicName": "Clinic name",
    "formStatus": "INCOMPLETE"
  },
  {
    "dateCreated": "14/12/2024",
    "formId": "S2406-0011",
    "patientReference": "21323132133",
    "clinicName": "Clinic name",
    "formStatus": "INCOMPLETE"
  },
  {
    "dateCreated": "14/12/2024",
    "formId": "S2406-0012",
    "patientReference": "21323132134",
    "clinicName": "Clinic name",
    "formStatus": "INCOMPLETE"
  },
  {
    "dateCreated": "14/12/2024",
    "formId": "S2406-0013",
    "patientReference": "21323132135",
    "clinicName": "Clinic name",
    "formStatus": "INCOMPLETE"
  },
  {
    "dateCreated": "14/12/2024",
    "formId": "S2406-0014",
    "patientReference": "21323132136",
    "clinicName": "Clinic name",
    "formStatus": "RETURNED"
  },
  {
    "dateCreated": "14/12/2024",
    "formId": "S2406-0015",
    "patientReference": "21323132137",
    "clinicName": "Clinic name",
    "formStatus": "SUBMITTED"
  },
  {
    "dateCreated": "15/12/2024",
    "formId": "S2406-0016",
    "patientReference": "21323132138",
    "clinicName": "Clinic name",
    "formStatus": "INCOMPLETE"
  },
  {
    "dateCreated": "15/12/2024",
    "formId": "S2406-0017",
    "patientReference": "21323132139",
    "clinicName": "Clinic name",
    "formStatus": "INCOMPLETE"
  },
  {
    "dateCreated": "15/12/2024",
    "formId": "S2406-0018",
    "patientReference": "21323132140",
    "clinicName": "Clinic name",
    "formStatus": "INCOMPLETE"
  },
  {
    "dateCreated": "15/12/2024",
    "formId": "S2406-0019",
    "patientReference": "21323132141",
    "clinicName": "Clinic name",
    "formStatus": "INCOMPLETE"
  },
  {
    "dateCreated": "15/12/2024",
    "formId": "S2406-0020",
    "patientReference": "21323132142",
    "clinicName": "Clinic name",
    "formStatus": "INCOMPLETE"
  },
  {
    "dateCreated": "15/12/2024",
    "formId": "S2406-0021",
    "patientReference": "21323132143",
    "clinicName": "Clinic name",
    "formStatus": "INCOMPLETE"
  },
  {
    "dateCreated": "15/12/2024",
    "formId": "S2406-0022",
    "patientReference": "21323132144",
    "clinicName": "Clinic name",
    "formStatus": "INCOMPLETE"
  },
  {
    "dateCreated": "15/12/2024",
    "formId": "S2406-0023",
    "patientReference": "21323132145",
    "clinicName": "Clinic name",
    "formStatus": "INCOMPLETE"
  },
  {
    "dateCreated": "15/12/2024",
    "formId": "S2406-0024",
    "patientReference": "21323132146",
    "clinicName": "Clinic name",
    "formStatus": "INCOMPLETE"
  },
  {
    "dateCreated": "15/12/2024",
    "formId": "S2406-0025",
    "patientReference": "21323132147",
    "clinicName": "Clinic name",
    "formStatus": "INCOMPLETE"
  },
  {
    "dateCreated": "15/12/2024",
    "formId": "S2406-0026",
    "patientReference": "21323132148",
    "clinicName": "Clinic name",
    "formStatus": "INCOMPLETE"
  },
  {
    "dateCreated": "15/12/2024",
    "formId": "S2406-0027",
    "patientReference": "21323132149",
    "clinicName": "Clinic name",
    "formStatus": "INCOMPLETE"
  },
  {
    "dateCreated": "15/12/2024",
    "formId": "S2406-0028",
    "patientReference": "21323132150",
    "clinicName": "Clinic name",
    "formStatus": "INCOMPLETE"
  },
  {
    "dateCreated": "15/12/2024",
    "formId": "S2406-0029",
    "patientReference": "21323132151",
    "clinicName": "Clinic name",
    "formStatus": "RETURNED"
  },
  {
    "dateCreated": "15/12/2024",
    "formId": "S2406-0030",
    "patientReference": "21323132152",
    "clinicName": "Clinic name",
    "formStatus": "SUBMITTED"
  },
  {
    "dateCreated": "16/12/2024",
    "formId": "S2406-0031",
    "patientReference": "21323132153",
    "clinicName": "Clinic name",
    "formStatus": "INCOMPLETE"
  },
  {
    "dateCreated": "16/12/2024",
    "formId": "S2406-0032",
    "patientReference": "21323132154",
    "clinicName": "Clinic name",
    "formStatus": "INCOMPLETE"
  },
  {
    "dateCreated": "16/12/2024",
    "formId": "S2406-0033",
    "patientReference": "21323132155",
    "clinicName": "Clinic name",
    "formStatus": "INCOMPLETE"
  },
  {
    "dateCreated": "16/12/2024",
    "formId": "S2406-0034",
    "patientReference": "21323132156",
    "clinicName": "Clinic name",
    "formStatus": "INCOMPLETE"
  },
  {
    "dateCreated": "16/12/2024",
    "formId": "S2406-0035",
    "patientReference": "21323132157",
    "clinicName": "Clinic name",
    "formStatus": "INCOMPLETE"
  },
  {
    "dateCreated": "16/12/2024",
    "formId": "S2406-0036",
    "patientReference": "21323132158",
    "clinicName": "Clinic name",
    "formStatus": "INCOMPLETE"
  },
  {
    "dateCreated": "16/12/2024",
    "formId": "S2406-0037",
    "patientReference": "21323132159",
    "clinicName": "Clinic name",
    "formStatus": "INCOMPLETE"
  },
  {
    "dateCreated": "16/12/2024",
    "formId": "S2406-0038",
    "patientReference": "21323132160",
    "clinicName": "Clinic name",
    "formStatus": "INCOMPLETE"
  },
  {
    "dateCreated": "16/12/2024",
    "formId": "S2406-0039",
    "patientReference": "21323132161",
    "clinicName": "Clinic name",
    "formStatus": "INCOMPLETE"
  },
  {
    "dateCreated": "16/12/2024",
    "formId": "S2406-0040",
    "patientReference": "21323132162",
    "clinicName": "Clinic name",
    "formStatus": "INCOMPLETE"
  },
  {
    "dateCreated": "16/12/2024",
    "formId": "S2406-0041",
    "patientReference": "21323132163",
    "clinicName": "Clinic name",
    "formStatus": "INCOMPLETE"
  },
  {
    "dateCreated": "16/12/2024",
    "formId": "S2406-0042",
    "patientReference": "21323132164",
    "clinicName": "Clinic name",
    "formStatus": "INCOMPLETE"
  },
  {
    "dateCreated": "16/12/2024",
    "formId": "S2406-0043",
    "patientReference": "21323132165",
    "clinicName": "Clinic name",
    "formStatus": "INCOMPLETE"
  },
  {
    "dateCreated": "16/12/2024",
    "formId": "S2406-0044",
    "patientReference": "21323132166",
    "clinicName": "Clinic name",
    "formStatus": "RETURNED"
  },
  {
    "dateCreated": "16/12/2024",
    "formId": "S2406-0045",
    "patientReference": "21323132167",
    "clinicName": "Clinic name",
    "formStatus": "SUBMITTED"
  },
  {
    "dateCreated": "17/12/2024",
    "formId": "S2406-0046",
    "patientReference": "21323132168",
    "clinicName": "Clinic name",
    "formStatus": "INCOMPLETE"
  },
  {
    "dateCreated": "17/12/2024",
    "formId": "S2406-0047",
    "patientReference": "21323132169",
    "clinicName": "Clinic name",
    "formStatus": "INCOMPLETE"
  },
  {
    "dateCreated": "17/12/2024",
    "formId": "S2406-0048",
    "patientReference": "21323132170",
    "clinicName": "Clinic name",
    "formStatus": "INCOMPLETE"
  },
  {
    "dateCreated": "17/12/2024",
    "formId": "S2406-0049",
    "patientReference": "21323132171",
    "clinicName": "Clinic name",
    "formStatus": "INCOMPLETE"
  },
  {
    "dateCreated": "17/12/2024",
    "formId": "S2406-0050",
    "patientReference": "21323132172",
    "clinicName": "Clinic name",
    "formStatus": "INCOMPLETE"
  },
  {
    "dateCreated": "17/12/2024",
    "formId": "S2406-0051",
    "patientReference": "21323132173",
    "clinicName": "Clinic name",
    "formStatus": "INCOMPLETE"
  },
  {
    "dateCreated": "17/12/2024",
    "formId": "S2406-0052",
    "patientReference": "21323132174",
    "clinicName": "Clinic name",
    "formStatus": "INCOMPLETE"
  },
  {
    "dateCreated": "17/12/2024",
    "formId": "S2406-0053",
    "patientReference": "21323132175",
    "clinicName": "Clinic name",
    "formStatus": "INCOMPLETE"
  },
  {
    "dateCreated": "17/12/2024",
    "formId": "S2406-0054",
    "patientReference": "21323132176",
    "clinicName": "Clinic name",
    "formStatus": "INCOMPLETE"
  },
  {
    "dateCreated": "17/12/2024",
    "formId": "S2406-0055",
    "patientReference": "21323132177",
    "clinicName": "Clinic name",
    "formStatus": "INCOMPLETE"
  },
  {
    "dateCreated": "17/12/2024",
    "formId": "S2406-0056",
    "patientReference": "21323132178",
    "clinicName": "Clinic name",
    "formStatus": "INCOMPLETE"
  },
  {
    "dateCreated": "17/12/2024",
    "formId": "S2406-0057",
    "patientReference": "21323132179",
    "clinicName": "Clinic name",
    "formStatus": "INCOMPLETE"
  },
  {
    "dateCreated": "17/12/2024",
    "formId": "S2406-0058",
    "patientReference": "21323132180",
    "clinicName": "Clinic name",
    "formStatus": "INCOMPLETE"
  },
  {
    "dateCreated": "17/12/2024",
    "formId": "S2406-0059",
    "patientReference": "21323132181",
    "clinicName": "Clinic name",
    "formStatus": "RETURNED"
  },
  {
    "dateCreated": "17/12/2024",
    "formId": "S2406-0060",
    "patientReference": "21323132182",
    "clinicName": "Clinic name",
    "formStatus": "SUBMITTED"
  },
  {
    "dateCreated": "18/12/2024",
    "formId": "S2406-0061",
    "patientReference": "21323132183",
    "clinicName": "Clinic name",
    "formStatus": "INCOMPLETE"
  },
  {
    "dateCreated": "18/12/2024",
    "formId": "S2406-0062",
    "patientReference": "21323132184",
    "clinicName": "Clinic name",
    "formStatus": "INCOMPLETE"
  },
  {
    "dateCreated": "18/12/2024",
    "formId": "S2406-0063",
    "patientReference": "21323132185",
    "clinicName": "Clinic name",
    "formStatus": "INCOMPLETE"
  },
  {
    "dateCreated": "18/12/2024",
    "formId": "S2406-0064",
    "patientReference": "21323132186",
    "clinicName": "Clinic name",
    "formStatus": "INCOMPLETE"
  },
  {
    "dateCreated": "18/12/2024",
    "formId": "S2406-0065",
    "patientReference": "21323132187",
    "clinicName": "Clinic name",
    "formStatus": "INCOMPLETE"
  },
  {
    "dateCreated": "18/12/2024",
    "formId": "S2406-0066",
    "patientReference": "21323132188",
    "clinicName": "Clinic name",
    "formStatus": "INCOMPLETE"
  },
  {
    "dateCreated": "18/12/2024",
    "formId": "S2406-0067",
    "patientReference": "21323132189",
    "clinicName": "Clinic name",
    "formStatus": "INCOMPLETE"
  },
  {
    "dateCreated": "18/12/2024",
    "formId": "S2406-0068",
    "patientReference": "21323132190",
    "clinicName": "Clinic name",
    "formStatus": "INCOMPLETE"
  },
  {
    "dateCreated": "18/12/2024",
    "formId": "S2406-0069",
    "patientReference": "21323132191",
    "clinicName": "Clinic name",
    "formStatus": "INCOMPLETE"
  },
  {
    "dateCreated": "18/12/2024",
    "formId": "S2406-0070",
    "patientReference": "21323132192",
    "clinicName": "Clinic name",
    "formStatus": "INCOMPLETE"
  },
  {
    "dateCreated": "18/12/2024",
    "formId": "S2406-0071",
    "patientReference": "21323132193",
    "clinicName": "Clinic name",
    "formStatus": "INCOMPLETE"
  },
  {
    "dateCreated": "18/12/2024",
    "formId": "S2406-0072",
    "patientReference": "21323132194",
    "clinicName": "Clinic name",
    "formStatus": "INCOMPLETE"
  },
  {
    "dateCreated": "18/12/2024",
    "formId": "S2406-0073",
    "patientReference": "21323132195",
    "clinicName": "Clinic name",
    "formStatus": "INCOMPLETE"
  },
  {
    "dateCreated": "18/12/2024",
    "formId": "S2406-0074",
    "patientReference": "21323132196",
    "clinicName": "Clinic name",
    "formStatus": "RETURNED"
  },
  {
    "dateCreated": "18/12/2024",
    "formId": "S2406-0075",
    "patientReference": "21323132197",
    "clinicName": "Clinic name",
    "formStatus": "SUBMITTED"
  },
  {
    "dateCreated": "19/12/2024",
    "formId": "S2406-0076",
    "patientReference": "21323132198",
    "clinicName": "Clinic name",
    "formStatus": "INCOMPLETE"
  },
  {
    "dateCreated": "19/12/2024",
    "formId": "S2406-0077",
    "patientReference": "21323132199",
    "clinicName": "Clinic name",
    "formStatus": "INCOMPLETE"
  },
  {
    "dateCreated": "19/12/2024",
    "formId": "S2406-0078",
    "patientReference": "21323132200",
    "clinicName": "Clinic name",
    "formStatus": "INCOMPLETE"
  },
  {
    "dateCreated": "19/12/2024",
    "formId": "S2406-0079",
    "patientReference": "21323132201",
    "clinicName": "Clinic name",
    "formStatus": "INCOMPLETE"
  },
  {
    "dateCreated": "19/12/2024",
    "formId": "S2406-0080",
    "patientReference": "21323132202",
    "clinicName": "Clinic name",
    "formStatus": "INCOMPLETE"
  },
  {
    "dateCreated": "19/12/2024",
    "formId": "S2406-0081",
    "patientReference": "21323132203",
    "clinicName": "Clinic name",
    "formStatus": "INCOMPLETE"
  },
  {
    "dateCreated": "19/12/2024",
    "formId": "S2406-0082",
    "patientReference": "21323132204",
    "clinicName": "Clinic name",
    "formStatus": "INCOMPLETE"
  },
  {
    "dateCreated": "19/12/2024",
    "formId": "S2406-0083",
    "patientReference": "21323132205",
    "clinicName": "Clinic name",
    "formStatus": "INCOMPLETE"
  },
  {
    "dateCreated": "19/12/2024",
    "formId": "S2406-0084",
    "patientReference": "21323132206",
    "clinicName": "Clinic name",
    "formStatus": "INCOMPLETE"
  },
  {
    "dateCreated": "19/12/2024",
    "formId": "S2406-0085",
    "patientReference": "21323132207",
    "clinicName": "Clinic name",
    "formStatus": "INCOMPLETE"
  },
  {
    "dateCreated": "19/12/2024",
    "formId": "S2406-0086",
    "patientReference": "21323132208",
    "clinicName": "Clinic name",
    "formStatus": "INCOMPLETE"
  },
  {
    "dateCreated": "19/12/2024",
    "formId": "S2406-0087",
    "patientReference": "21323132209",
    "clinicName": "Clinic name",
    "formStatus": "INCOMPLETE"
  },
  {
    "dateCreated": "19/12/2024",
    "formId": "S2406-0088",
    "patientReference": "21323132210",
    "clinicName": "Clinic name",
    "formStatus": "INCOMPLETE"
  },
  {
    "dateCreated": "19/12/2024",
    "formId": "S2406-0089",
    "patientReference": "21323132211",
    "clinicName": "Clinic name",
    "formStatus": "RETURNED"
  },
  {
    "dateCreated": "19/12/2024",
    "formId": "S2406-0090",
    "patientReference": "21323132212",
    "clinicName": "Clinic name",
    "formStatus": "SUBMITTED"
  },
  {
    "dateCreated": "20/12/2024",
    "formId": "S2406-0091",
    "patientReference": "21323132213",
    "clinicName": "Clinic name",
    "formStatus": "INCOMPLETE"
  },
  {
    "dateCreated": "20/12/2024",
    "formId": "S2406-0092",
    "patientReference": "21323132214",
    "clinicName": "Clinic name",
    "formStatus": "INCOMPLETE"
  },
  {
    "dateCreated": "20/12/2024",
    "formId": "S2406-0093",
    "patientReference": "21323132215",
    "clinicName": "Clinic name",
    "formStatus": "INCOMPLETE"
  },
  {
    "dateCreated": "20/12/2024",
    "formId": "S2406-0094",
    "patientReference": "21323132216",
    "clinicName": "Clinic name",
    "formStatus": "INCOMPLETE"
  },
  {
    "dateCreated": "20/12/2024",
    "formId": "S2406-0095",
    "patientReference": "21323132217",
    "clinicName": "Clinic name",
    "formStatus": "INCOMPLETE"
  },
  {
    "dateCreated": "20/12/2024",
    "formId": "S2406-0096",
    "patientReference": "21323132218",
    "clinicName": "Clinic name",
    "formStatus": "INCOMPLETE"
  },
  {
    "dateCreated": "20/12/2024",
    "formId": "S2406-0097",
    "patientReference": "21323132219",
    "clinicName": "Clinic name",
    "formStatus": "INCOMPLETE"
  },
  {
    "dateCreated": "20/12/2024",
    "formId": "S2406-0098",
    "patientReference": "21323132220",
    "clinicName": "Clinic name",
    "formStatus": "INCOMPLETE"
  },
  {
    "dateCreated": "20/12/2024",
    "formId": "S2406-0099",
    "patientReference": "21323132221",
    "clinicName": "Clinic name",
    "formStatus": "INCOMPLETE"
  },
  {
    "dateCreated": "20/12/2024",
    "formId": "S2406-0100",
    "patientReference": "21323132222",
    "clinicName": "Clinic name",
    "formStatus": "INCOMPLETE"
  },
  {
    "dateCreated": "20/12/2024",
    "formId": "S2406-0101",
    "patientReference": "21323132223",
    "clinicName": "Clinic name",
    "formStatus": "INCOMPLETE"
  },
  {
    "dateCreated": "20/12/2024",
    "formId": "S2406-0102",
    "patientReference": "21323132224",
    "clinicName": "Clinic name",
    "formStatus": "INCOMPLETE"
  },
  {
    "dateCreated": "20/12/2024",
    "formId": "S2406-0103",
    "patientReference": "21323132225",
    "clinicName": "Clinic name",
    "formStatus": "INCOMPLETE"
  },
  {
    "dateCreated": "20/12/2024",
    "formId": "S2406-0104",
    "patientReference": "21323132226",
    "clinicName": "Clinic name",
    "formStatus": "RETURNED"
  },
  {
    "dateCreated": "20/12/2024",
    "formId": "S2406-0105",
    "patientReference": "21323132227",
    "clinicName": "Clinic name",
    "formStatus": "SUBMITTED"
  },
  {
    "dateCreated": "21/12/2024",
    "formId": "S2406-0106",
    "patientReference": "21323132228",
    "clinicName": "Clinic name",
    "formStatus": "INCOMPLETE"
  },
  {
    "dateCreated": "21/12/2024",
    "formId": "S2406-0107",
    "patientReference": "21323132229",
    "clinicName": "Clinic name",
    "formStatus": "INCOMPLETE"
  },
  {
    "dateCreated": "21/12/2024",
    "formId": "S2406-0108",
    "patientReference": "21323132230",
    "clinicName": "Clinic name",
    "formStatus": "INCOMPLETE"
  },
  {
    "dateCreated": "21/12/2024",
    "formId": "S2406-0109",
    "patientReference": "21323132231",
    "clinicName": "Clinic name",
    "formStatus": "INCOMPLETE"
  },
  {
    "dateCreated": "21/12/2024",
    "formId": "S2406-0110",
    "patientReference": "21323132232",
    "clinicName": "Clinic name",
    "formStatus": "INCOMPLETE"
  },
  {
    "dateCreated": "21/12/2024",
    "formId": "S2406-0111",
    "patientReference": "21323132233",
    "clinicName": "Clinic name",
    "formStatus": "INCOMPLETE"
  },
  {
    "dateCreated": "21/12/2024",
    "formId": "S2406-0112",
    "patientReference": "21323132234",
    "clinicName": "Clinic name",
    "formStatus": "INCOMPLETE"
  },
  {
    "dateCreated": "21/12/2024",
    "formId": "S2406-0113",
    "patientReference": "21323132235",
    "clinicName": "Clinic name",
    "formStatus": "INCOMPLETE"
  },
  {
    "dateCreated": "21/12/2024",
    "formId": "S2406-0114",
    "patientReference": "21323132236",
    "clinicName": "Clinic name",
    "formStatus": "INCOMPLETE"
  },
  {
    "dateCreated": "21/12/2024",
    "formId": "S2406-0115",
    "patientReference": "21323132237",
    "clinicName": "Clinic name",
    "formStatus": "INCOMPLETE"
  },
  {
    "dateCreated": "21/12/2024",
    "formId": "S2406-0116",
    "patientReference": "21323132238",
    "clinicName": "Clinic name",
    "formStatus": "INCOMPLETE"
  },
  {
    "dateCreated": "21/12/2024",
    "formId": "S2406-0117",
    "patientReference": "21323132239",
    "clinicName": "Clinic name",
    "formStatus": "INCOMPLETE"
  },
  {
    "dateCreated": "21/12/2024",
    "formId": "S2406-0118",
    "patientReference": "21323132240",
    "clinicName": "Clinic name",
    "formStatus": "INCOMPLETE"
  },
  {
    "dateCreated": "21/12/2024",
    "formId": "S2406-0119",
    "patientReference": "21323132241",
    "clinicName": "Clinic name",
    "formStatus": "RETURNED"
  },
  {
    "dateCreated": "21/12/2024",
    "formId": "S2406-0120",
    "patientReference": "21323132242",
    "clinicName": "Clinic name",
    "formStatus": "SUBMITTED"
  },
  {
    "dateCreated": "22/12/2024",
    "formId": "S2406-0121",
    "patientReference": "21323132243",
    "clinicName": "Clinic name",
    "formStatus": "INCOMPLETE"
  },
  {
    "dateCreated": "22/12/2024",
    "formId": "S2406-0122",
    "patientReference": "21323132244",
    "clinicName": "Clinic name",
    "formStatus": "INCOMPLETE"
  },
  {
    "dateCreated": "22/12/2024",
    "formId": "S2406-0123",
    "patientReference": "21323132245",
    "clinicName": "Clinic name",
    "formStatus": "INCOMPLETE"
  },
  {
    "dateCreated": "22/12/2024",
    "formId": "S2406-0124",
    "patientReference": "21323132246",
    "clinicName": "Clinic name",
    "formStatus": "INCOMPLETE"
  },
  {
    "dateCreated": "22/12/2024",
    "formId": "S2406-0125",
    "patientReference": "21323132247",
    "clinicName": "Clinic name",
    "formStatus": "INCOMPLETE"
  },
  {
    "dateCreated": "22/12/2024",
    "formId": "S2406-0126",
    "patientReference": "21323132248",
    "clinicName": "Clinic name",
    "formStatus": "INCOMPLETE"
  },
  {
    "dateCreated": "22/12/2024",
    "formId": "S2406-0127",
    "patientReference": "21323132249",
    "clinicName": "Clinic name",
    "formStatus": "INCOMPLETE"
  },
  {
    "dateCreated": "22/12/2024",
    "formId": "S2406-0128",
    "patientReference": "21323132250",
    "clinicName": "Clinic name",
    "formStatus": "INCOMPLETE"
  },
  {
    "dateCreated": "22/12/2024",
    "formId": "S2406-0129",
    "patientReference": "21323132251",
    "clinicName": "Clinic name",
    "formStatus": "INCOMPLETE"
  },
  {
    "dateCreated": "22/12/2024",
    "formId": "S2406-0130",
    "patientReference": "21323132252",
    "clinicName": "Clinic name",
    "formStatus": "INCOMPLETE"
  },
  {
    "dateCreated": "22/12/2024",
    "formId": "S2406-0131",
    "patientReference": "21323132253",
    "clinicName": "Clinic name",
    "formStatus": "INCOMPLETE"
  },
  {
    "dateCreated": "22/12/2024",
    "formId": "S2406-0132",
    "patientReference": "21323132254",
    "clinicName": "Clinic name",
    "formStatus": "INCOMPLETE"
  },
  {
    "dateCreated": "22/12/2024",
    "formId": "S2406-0133",
    "patientReference": "21323132255",
    "clinicName": "Clinic name",
    "formStatus": "INCOMPLETE"
  },
  {
    "dateCreated": "22/12/2024",
    "formId": "S2406-0134",
    "patientReference": "21323132256",
    "clinicName": "Clinic name",
    "formStatus": "RETURNED"
  },
  {
    "dateCreated": "22/12/2024",
    "formId": "S2406-0135",
    "patientReference": "21323132257",
    "clinicName": "Clinic name",
    "formStatus": "SUBMITTED"
  },
  {
    "dateCreated": "23/12/2024",
    "formId": "S2406-0136",
    "patientReference": "21323132258",
    "clinicName": "Clinic name",
    "formStatus": "INCOMPLETE"
  },
  {
    "dateCreated": "23/12/2024",
    "formId": "S2406-0137",
    "patientReference": "21323132259",
    "clinicName": "Clinic name",
    "formStatus": "INCOMPLETE"
  },
  {
    "dateCreated": "23/12/2024",
    "formId": "S2406-0138",
    "patientReference": "21323132260",
    "clinicName": "Clinic name",
    "formStatus": "INCOMPLETE"
  },
  {
    "dateCreated": "23/12/2024",
    "formId": "S2406-0139",
    "patientReference": "21323132261",
    "clinicName": "Clinic name",
    "formStatus": "INCOMPLETE"
  },
  {
    "dateCreated": "23/12/2024",
    "formId": "S2406-0140",
    "patientReference": "21323132262",
    "clinicName": "Clinic name",
    "formStatus": "INCOMPLETE"
  },
  {
    "dateCreated": "23/12/2024",
    "formId": "S2406-0141",
    "patientReference": "21323132263",
    "clinicName": "Clinic name",
    "formStatus": "INCOMPLETE"
  },
  {
    "dateCreated": "23/12/2024",
    "formId": "S2406-0142",
    "patientReference": "21323132264",
    "clinicName": "Clinic name",
    "formStatus": "INCOMPLETE"
  },
  {
    "dateCreated": "23/12/2024",
    "formId": "S2406-0143",
    "patientReference": "21323132265",
    "clinicName": "Clinic name",
    "formStatus": "INCOMPLETE"
  },
  {
    "dateCreated": "23/12/2024",
    "formId": "S2406-0144",
    "patientReference": "21323132266",
    "clinicName": "Clinic name",
    "formStatus": "INCOMPLETE"
  },
  {
    "dateCreated": "23/12/2024",
    "formId": "S2406-0145",
    "patientReference": "21323132267",
    "clinicName": "Clinic name",
    "formStatus": "INCOMPLETE"
  },
  {
    "dateCreated": "23/12/2024",
    "formId": "S2406-0146",
    "patientReference": "21323132268",
    "clinicName": "Clinic name",
    "formStatus": "INCOMPLETE"
  },
  {
    "dateCreated": "23/12/2024",
    "formId": "S2406-0147",
    "patientReference": "21323132269",
    "clinicName": "Clinic name",
    "formStatus": "INCOMPLETE"
  },
  {
    "dateCreated": "23/12/2024",
    "formId": "S2406-0148",
    "patientReference": "21323132270",
    "clinicName": "Clinic name",
    "formStatus": "INCOMPLETE"
  },
  {
    "dateCreated": "23/12/2024",
    "formId": "S2406-0149",
    "patientReference": "21323132271",
    "clinicName": "Clinic name",
    "formStatus": "RETURNED"
  },
  {
    "dateCreated": "23/12/2024",
    "formId": "S2406-0150",
    "patientReference": "21323132272",
    "clinicName": "Clinic name",
    "formStatus": "SUBMITTED"
  }
]